{
    "title": "Ken Liao",
    "description": "www.kenliao.com",
    "keywords": "Ken Liao,www.kenliao.com",
    "author": "Ken Liao",
    "logo_img": "./img/icon/logo.png",
    "logo_text_1": "kenliao",
    "logo_text_2": "com",
    "github": "imsyy",
    "qq": "1539250352",
    "email": "one@imsyy.top",
    "bilibili": "98544142",
    "telegram": "bottom_user",
    "link_1": [
        "https://www.moyupai.com/",
        "fa-solid fa-compass",
        "墨鱼派"
    ],
    "link_2": [
        "https://www.wuzeipai.com/",
        "fa-solid fa-blog",
        "乌贼派"
    ],
    "link_3": [
        "https://music.163.com/",
        "fa-solid fa-music",
        "音乐"
    ],
    "link_4": [
        "https://nav.imsyy.top/",
        "fa-solid fa-compass",
        "起始页"
    ],
    "link_5": [
        "https://web.imsyy.top/",
        "fa-solid fa-book-bookmark",
        "网址集"
    ],
    "link_6": [
        "https://lab.imsyy.top/",
        "fa-solid fa-flask",
        "实验室"
    ],
    "Copyright_text": "Ken Liao",
    "beian": "粤ICP备14054021号"
}